[
      {
            "id": "Null",
            "name": "thien ly oi 2",
            "day": "1/1/00",
            "score": "10",
            "link": "https://open.spotify.com/track/3ztP5O7dJSha2PG429eUCb",
            "img": "/Users/minhhaonguyen/Downloads/Thi\u00ean l\u00fd \u01a1i'.png"
      },
      {
            "id": "Null",
            "name": "skibidi",
            "day": "1/1/00",
            "score": "",
            "link": "https://www.youtube.com/shorts/EXm0RfxrVNM",
            "img": "/Users/minhhaonguyen/Downloads/skibidi.jpeg"
      },
      {
            "id": "Null",
            "name": "eklwwfwnlad",
            "day": "1/1/00",
            "score": "8",
            "link": "https://www.youtube.com/watch?v=JGwWNGJdvx8",
            "img": "/Users/minhhaonguyen/Desktop/PTI02-HB/Images/shape of you.png"
      }
]